pyords/__init__.py
pyords/cluster/__init__.py
pyords/cluster/algorithms.py
pyords/cluster/implementations.py
pyords/cluster/visualizations.py
pyords/core/__init__.py
pyords/core/bundles.py
pyords/distance/__init__.py
pyords/distance/haversine.py
pyords/genetic_algorithm/__init__.py
pyords/genetic_algorithm/algorithms.py
pyords/genetic_algorithm/environments.py
pyords/genetic_algorithm/visualizations.py
tests/__init__.py
tests/common.py
tests/test_bundles.py
tests/test_dbscan.py
tests/test_dfis.py
tests/test_distance_matrix.py
tests/test_genetic_algorithm_vrp.py
tests/test_haversine.py
tests/test_kmeans_greenfield.py
pyords-0.0.9.dist-info/LICENSE
pyords-0.0.9.dist-info/METADATA
pyords-0.0.9.dist-info/WHEEL
pyords-0.0.9.dist-info/entry_points.txt
pyords-0.0.9.dist-info/top_level.txt
pyords-0.0.9.dist-info/RECORD
