Metadata-Version: 2.1
Name: pyords
Version: 0.0.9
Summary: A python package for operations research and data science problems.
Home-page: https://github.com/christopherpryer/pyords
Author: Chris Pryer
Author-email: christophpryer@gmail.com
License: PUBLIC
Platform: UNKNOWN
Requires-Dist: atomicwrites (==1.4.0)
Requires-Dist: attrs (==19.3.0)
Requires-Dist: colorama (==0.4.3)
Requires-Dist: cycler (==0.10.0)
Requires-Dist: gprof2dot (==2019.11.30)
Requires-Dist: haversine (==2.2.0)
Requires-Dist: importlib-metadata (==1.6.0)
Requires-Dist: kiwisolver (==1.2.0)
Requires-Dist: matplotlib (==3.2.1)
Requires-Dist: more-itertools (==8.3.0)
Requires-Dist: numpy (==1.18.4)
Requires-Dist: ortools
Requires-Dist: packaging (==20.4)
Requires-Dist: pandas (==1.0.4)
Requires-Dist: pluggy (==0.13.1)
Requires-Dist: protobuf (==3.12.2)
Requires-Dist: py (==1.8.1)
Requires-Dist: pyparsing (==2.4.7)
Requires-Dist: pytest (==5.4.2)
Requires-Dist: pytest-profiling (==1.7.0)
Requires-Dist: python-dateutil (==2.8.1)
Requires-Dist: pytz (==2020.1)
Requires-Dist: six (==1.15.0)
Requires-Dist: wcwidth (==0.2.2)
Requires-Dist: zipp (==3.1.0)
